gradle.properties
hexdoc_hexoverpowered/__gradle_version__.py
hexdoc_hexoverpowered/__init__.py
hexdoc_hexoverpowered/__version__.py
hexdoc_hexoverpowered/_hooks.py
hexdoc_hexoverpowered/py.typed
hexdoc_hexoverpowered/_export/.gitignore
hexdoc_hexoverpowered/_export/__init__.py
hexdoc_hexoverpowered/_export/generated/__init__.py
hexdoc_hexoverpowered/_export/generated/hexoverpowered.hexdoc.json
hexdoc_hexoverpowered/_export/generated/hexoverpowered.patterns.hexdoc.json
hexdoc_hexoverpowered/_export/generated/assets/hexcasting/patchouli_books/thehexbook/en_us/entries/pages.json
hexdoc_hexoverpowered/_export/generated/assets/hexoverpowered/lang/en_us.flatten.json5
hexdoc_hexoverpowered/_export/generated/assets/hexoverpowered/lang/en_us.json
hexdoc_hexoverpowered/_export/generated/assets/hexoverpowered/lang/zh_cn.json
hexdoc_hexoverpowered/_export/generated/assets/hexoverpowered/textures/gui/media_bar.png
hexdoc_hexoverpowered/_export/generated/data/hexcasting/tags/action/per_world_pattern.json
hexdoc_hexoverpowered/_templates/__init__.py
hexdoc_hexoverpowered-0.11.0.1.1.dist-info/METADATA
hexdoc_hexoverpowered-0.11.0.1.1.dist-info/WHEEL
hexdoc_hexoverpowered-0.11.0.1.1.dist-info/entry_points.txt
hexdoc_hexoverpowered-0.11.0.1.1.dist-info/licenses/LICENSE.txt
hexdoc_hexoverpowered-0.11.0.1.1.dist-info/RECORD
