Metadata-Version: 2.4
Name: hexdoc-hexoverpowered
Version: 0.11.0.1.1
Summary: Python web book docgen and hexdoc plugin for HexOverpowered.
Project-URL: Homepage, https://yukkuric.github.io/HexOverpowered/
Project-URL: Source, https://github.com/YukkuriC/HexOverpowered
Author: YukkuriC
License-File: LICENSE.txt
Keywords: hexdoc
Requires-Python: >=3.11
Requires-Dist: hexdoc-hexcasting~=0.11.3.1.0
Provides-Extra: dev
Requires-Dist: ruff~=0.11.2; extra == 'dev'
